[{"name":"Aruba","continent":"North America","iso":"ABW"},{"name":"Afghanistan","continent":"Asia","iso":"AFG"},{"name":"Angola","continent":"Africa","iso":"AGO"},{"name":"Albania","continent":"Europe","iso":"ALB"},{"name":"Andorra","continent":"Europe","iso":"AND"},{"name":"United Arab Emirates","continent":"Asia","iso":"ARE"},{"name":"Argentina","continent":"South America","iso":"ARG"},{"name":"Armenia","continent":"Asia","iso":"ARM"},{"name":"American Samoa","continent":"Oceania","iso":"ASM"},{"name":"Antigua and Barbuda","continent":"North America","iso":"ATG"},{"name":"Australia","continent":"Oceania","iso":"AUS"},{"name":"Austria","continent":"Europe","iso":"AUT"},{"name":"Azerbaijan","continent":"Asia","iso":"AZE"},{"name":"Burundi","continent":"Africa","iso":"BDI"},{"name":"Belgium","continent":"Europe","iso":"BEL"},{"name":"Benin","continent":"Africa","iso":"BEN"},{"name":"Burkina Faso","continent":"Africa","iso":"BFA"},{"name":"Bangladesh","continent":"Asia","iso":"BGD"},{"name":"Bulgaria","continent":"Europe","iso":"BGR"},{"name":"Bahrain","continent":"Asia","iso":"BHR"},{"name":"Bahamas, The","continent":"North America","iso":"BHS"},{"name":"Bosnia and Herzegovina","continent":"Europe","iso":"BIH"},{"name":"Belarus","continent":"Europe","iso":"BLR"},{"name":"Belize","continent":"North America","iso":"BLZ"},{"name":"Bermuda","continent":"North America","iso":"BMU"},{"name":"Bolivia","continent":"South America","iso":"BOL"},{"name":"Brazil","continent":"South America","iso":"BRA"},{"name":"Barbados","continent":"North America","iso":"BRB"},{"name":"Brunei Darussalam","continent":"Asia","iso":"BRN"},{"name":"Bhutan","continent":"Asia","iso":"BTN"},{"name":"Botswana","continent":"Africa","iso":"BWA"},{"name":"Central African Republic","continent":"Africa","iso":"CAF"},{"name":"Canada","continent":"North America","iso":"CAN"},{"name":"Switzerland","continent":"Europe","iso":"CHE"},{"name":"Channel Islands","continent":"Europe","iso":"CHI"},{"name":"Chile","continent":"South America","iso":"CHL"},{"name":"China","continent":"Asia","iso":"CHN"},{"name":"Cote d'Ivoire","continent":"Africa","iso":"CIV"},{"name":"Cameroon","continent":"Africa","iso":"CMR"},{"name":"Congo, Dem. Rep.","continent":"Africa","iso":"COD"},{"name":"Congo, Rep.","continent":"Africa","iso":"COG"},{"name":"Colombia","continent":"South America","iso":"COL"},{"name":"Comoros","continent":"Africa","iso":"COM"},{"name":"Cabo Verde","continent":"Africa","iso":"CPV"},{"name":"Costa Rica","continent":"North America","iso":"CRI"},{"name":"Cuba","continent":"North America","iso":"CUB"},{"name":"Curacao","continent":"South America","iso":"CUW"},{"name":"Cayman Islands","continent":"North America","iso":"CYM"},{"name":"Cyprus","continent":"Asia","iso":"CYP"},{"name":"Czech Republic","continent":"Europe","iso":"CZE"},{"name":"Germany","continent":"Europe","iso":"DEU"},{"name":"Djibouti","continent":"Africa","iso":"DJI"},{"name":"Dominica","continent":"North America","iso":"DMA"},{"name":"Denmark","continent":"Europe","iso":"DNK"},{"name":"Dominican Republic","continent":"North America","iso":"DOM"},{"name":"Algeria","continent":"Africa","iso":"DZA"},{"name":"Ecuador","continent":"South America","iso":"ECU"},{"name":"Egypt, Arab Rep.","continent":"Africa","iso":"EGY"},{"name":"Eritrea","continent":"Africa","iso":"ERI"},{"name":"Spain","continent":"Europe","iso":"ESP"},{"name":"Estonia","continent":"Europe","iso":"EST"},{"name":"Ethiopia","continent":"Africa","iso":"ETH"},{"name":"Finland","continent":"Europe","iso":"FIN"},{"name":"Fiji","continent":"Oceania","iso":"FJI"},{"name":"France","continent":"Europe","iso":"FRA"},{"name":"Faroe Islands","continent":"Europe","iso":"FRO"},{"name":"Micronesia, Fed. Sts.","continent":"Oceania","iso":"FSM"},{"name":"Gabon","continent":"Africa","iso":"GAB"},{"name":"United Kingdom","continent":"Europe","iso":"GBR"},{"name":"Georgia","continent":"Asia","iso":"GEO"},{"name":"Ghana","continent":"Africa","iso":"GHA"},{"name":"Gibraltar","continent":"Europe","iso":"GIB"},{"name":"Guinea","continent":"Africa","iso":"GIN"},{"name":"Gambia, The","continent":"Africa","iso":"GMB"},{"name":"Guinea-Bissau","continent":"Africa","iso":"GNB"},{"name":"Equatorial Guinea","continent":"Africa","iso":"GNQ"},{"name":"Greece","continent":"Europe","iso":"GRC"},{"name":"Grenada","continent":"North America","iso":"GRD"},{"name":"Greenland","continent":"Europe","iso":"GRL"},{"name":"Guatemala","continent":"North America","iso":"GTM"},{"name":"Guam","continent":"Oceania","iso":"GUM"},{"name":"Guyana","continent":"South America","iso":"GUY"},{"name":"Hong Kong SAR","continent":"Asia","iso":"HKG"},{"name":"Honduras","continent":"North America","iso":"HND"},{"name":"Croatia","continent":"Europe","iso":"HRV"},{"name":"Haiti","continent":"North America","iso":"HTI"},{"name":"Hungary","continent":"Europe","iso":"HUN"},{"name":"Indonesia","continent":"Asia","iso":"IDN"},{"name":"Isle of Man","continent":"Europe","iso":"IMN"},{"name":"India","continent":"Asia","iso":"IND"},{"name":"Ireland","continent":"Europe","iso":"IRL"},{"name":"Iran, Islamic Rep.","continent":"Asia","iso":"IRN"},{"name":"Iraq","continent":"Asia","iso":"IRQ"},{"name":"Iceland","continent":"Europe","iso":"ISL"},{"name":"Israel","continent":"Asia","iso":"ISR"},{"name":"Italy","continent":"Europe","iso":"ITA"},{"name":"Jamaica","continent":"North America","iso":"JAM"},{"name":"Jordan","continent":"Asia","iso":"JOR"},{"name":"Japan","continent":"Asia","iso":"JPN"},{"name":"Kazakhstan","continent":"Asia","iso":"KAZ"},{"name":"Kenya","continent":"Africa","iso":"KEN"},{"name":"Kyrgyz Republic","continent":"Asia","iso":"KGZ"},{"name":"Cambodia","continent":"Asia","iso":"KHM"},{"name":"Kiribati","continent":"Oceania","iso":"KIR"},{"name":"St. Kitts and Nevis","continent":"North America","iso":"KNA"},{"name":"Korea, Rep.","continent":"Asia","iso":"KOR"},{"name":"Kuwait","continent":"Asia","iso":"KWT"},{"name":"Lao PDR","continent":"Asia","iso":"LAO"},{"name":"Lebanon","continent":"Asia","iso":"LBN"},{"name":"Liberia","continent":"Africa","iso":"LBR"},{"name":"Libya","continent":"Africa","iso":"LBY"},{"name":"St. Lucia","continent":"North America","iso":"LCA"},{"name":"Liechtenstein","continent":"Europe","iso":"LIE"},{"name":"Sri Lanka","continent":"Asia","iso":"LKA"},{"name":"Lesotho","continent":"Africa","iso":"LSO"},{"name":"Lithuania","continent":"Europe","iso":"LTU"},{"name":"Luxembourg","continent":"Europe","iso":"LUX"},{"name":"Latvia","continent":"Europe","iso":"LVA"},{"name":"Macao SAR, China","continent":"Asia","iso":"MAC"},{"name":"St. Martin (French part)","continent":"Europe","iso":"MAF"},{"name":"Morocco","continent":"Africa","iso":"MAR"},{"name":"Monaco","continent":"Europe","iso":"MCO"},{"name":"Moldova","continent":"Europe","iso":"MDA"},{"name":"Madagascar","continent":"Africa","iso":"MDG"},{"name":"Maldives","continent":"Asia","iso":"MDV"},{"name":"Mexico","continent":"North America","iso":"MEX"},{"name":"Marshall Islands","continent":"Oceania","iso":"MHL"},{"name":"Macedonia, FYR","continent":"Europe","iso":"MKD"},{"name":"Mali","continent":"Africa","iso":"MLI"},{"name":"Malta","continent":"Europe","iso":"MLT"},{"name":"Myanmar","continent":"Asia","iso":"MMR"},{"name":"Montenegro","continent":"Europe","iso":"MNE"},{"name":"Mongolia","continent":"Asia","iso":"MNG"},{"name":"Northern Mariana Islands","continent":"Europe","iso":"MNP"},{"name":"Mozambique","continent":"Africa","iso":"MOZ"},{"name":"Mauritania","continent":"Africa","iso":"MRT"},{"name":"Mauritius","continent":"Africa","iso":"MUS"},{"name":"Malawi","continent":"Africa","iso":"MWI"},{"name":"Malaysia","continent":"Asia","iso":"MYS"},{"name":"Namibia","continent":"Africa","iso":"NAM"},{"name":"New Caledonia","continent":"Europe","iso":"NCL"},{"name":"Niger","continent":"Africa","iso":"NER"},{"name":"Nigeria","continent":"Africa","iso":"NGA"},{"name":"Nicaragua","continent":"North America","iso":"NIC"},{"name":"Netherlands","continent":"Europe","iso":"NLD"},{"name":"Norway","continent":"Europe","iso":"NOR"},{"name":"Nepal","continent":"Asia","iso":"NPL"},{"name":"Nauru","continent":"Oceania","iso":"NRU"},{"name":"New Zealand","continent":"Oceania","iso":"NZL"},{"name":"Oman","continent":"Asia","iso":"OMN"},{"name":"Pakistan","continent":"Asia","iso":"PAK"},{"name":"Panama","continent":"North America","iso":"PAN"},{"name":"Peru","continent":"South America","iso":"PER"},{"name":"Philippines","continent":"Asia","iso":"PHL"},{"name":"Palau","continent":"Oceania","iso":"PLW"},{"name":"Papua New Guinea","continent":"Oceania","iso":"PNG"},{"name":"Poland","continent":"Europe","iso":"POL"},{"name":"Puerto Rico","continent":"North America","iso":"PRI"},{"name":"Korea, Dem. People’s Rep.","continent":"Asia","iso":"PRK"},{"name":"Portugal","continent":"Europe","iso":"PRT"},{"name":"Paraguay","continent":"South America","iso":"PRY"},{"name":"West Bank and Gaza","continent":"Asia","iso":"PSE"},{"name":"Pacific island small states","continent":"Europe","iso":"PSS"},{"name":"French Polynesia","continent":"Asia","iso":"PYF"},{"name":"Qatar","continent":"Asia","iso":"QAT"},{"name":"Romania","continent":"Europe","iso":"ROU"},{"name":"Russian Federation","continent":"Europe","iso":"RUS"},{"name":"Rwanda","continent":"Africa","iso":"RWA"},{"name":"Saudi Arabia","continent":"Asia","iso":"SAU"},{"name":"Sudan","continent":"Africa","iso":"SDN"},{"name":"Senegal","continent":"Africa","iso":"SEN"},{"name":"Singapore","continent":"Asia","iso":"SGP"},{"name":"Solomon Islands","continent":"Oceania","iso":"SLB"},{"name":"Sierra Leone","continent":"Africa","iso":"SLE"},{"name":"El Salvador","continent":"North America","iso":"SLV"},{"name":"San Marino","continent":"Europe","iso":"SMR"},{"name":"Somalia","continent":"Africa","iso":"SOM"},{"name":"Serbia","continent":"Europe","iso":"SRB"},{"name":"South Sudan","continent":"Africa","iso":"SSD"},{"name":"Sao Tome and Principe","continent":"Africa","iso":"STP"},{"name":"Suriname","continent":"South America","iso":"SUR"},{"name":"Slovak Republic","continent":"Europe","iso":"SVK"},{"name":"Slovenia","continent":"Europe","iso":"SVN"},{"name":"Sweden","continent":"Europe","iso":"SWE"},{"name":"Eswatini","continent":"Africa","iso":"SWZ"},{"name":"Sint Maarten (Dutch part)","continent":"Africa","iso":"SXM"},{"name":"Seychelles","continent":"Africa","iso":"SYC"},{"name":"Syrian Arab Republic","continent":"Asia","iso":"SYR"},{"name":"Turks and Caicos Islands","continent":"North America","iso":"TCA"},{"name":"Chad","continent":"Africa","iso":"TCD"},{"name":"Togo","continent":"Africa","iso":"TGO"},{"name":"Thailand","continent":"Asia","iso":"THA"},{"name":"Tajikistan","continent":"Asia","iso":"TJK"},{"name":"Turkmenistan","continent":"Asia","iso":"TKM"},{"name":"Timor-Leste","continent":"Asia","iso":"TLS"},{"name":"Tonga","continent":"Oceania","iso":"TON"},{"name":"Trinidad and Tobago","continent":"North America","iso":"TTO"},{"name":"Tunisia","continent":"Africa","iso":"TUN"},{"name":"Turkey","continent":"Asia","iso":"TUR"},{"name":"Tuvalu","continent":"Oceania","iso":"TUV"},{"name":"Tanzania","continent":"Africa","iso":"TZA"},{"name":"Uganda","continent":"Africa","iso":"UGA"},{"name":"Ukraine","continent":"Europe","iso":"UKR"},{"name":"Uruguay","continent":"South America","iso":"URY"},{"name":"United States","continent":"North America","iso":"USA"},{"name":"Uzbekistan","continent":"Asia","iso":"UZB"},{"name":"St. Vincent and the Grenadines","continent":"North America","iso":"VCT"},{"name":"Venezuela, RB","continent":"South America","iso":"VEN"},{"name":"British Virgin Islands","continent":"North America","iso":"VGB"},{"name":"Virgin Islands (U.S.)","continent":"North America","iso":"VIR"},{"name":"Vietnam","continent":"Asia","iso":"VNM"},{"name":"Vanuatu","continent":"Oceania","iso":"VUT"},{"name":"Samoa","continent":"Oceania","iso":"WSM"},{"name":"Kosovo","continent":"Europe","iso":"XKX"},{"name":"Yemen, Rep.","continent":"Asia","iso":"YEM"},{"name":"South Africa","continent":"Africa","iso":"ZAF"},{"name":"Zambia","continent":"Africa","iso":"ZMB"},{"name":"Zimbabwe","continent":"Africa","iso":"ZWE"},{},{},{},{},{},{},{},{},{}]